examples/__init__.py
examples/admin.py
examples/base.py
examples/main.py
fastapi_integration/__init__.py
fastapi_integration/common.py
fastapi_integration/config.py
fastapi_integration/db.py
fastapi_integration/dependencies.py
fastapi_integration/exceptions.py
fastapi_integration/features.py
fastapi_integration/models.py
fastapi_integration/admin/__init__.py
fastapi_integration/admin/generator.py
fastapi_integration/auth/__init__.py
fastapi_integration/auth/routers.py
fastapi_integration/auth/schemas.py
fastapi_integration/auth/utils.py
fastapi_integration/generic/__init__.py
fastapi_integration/generic/crud.py
fastapi_integration/generic/views.py
fastapi_integration/orm/__init__.py
fastapi_integration/orm/base.py
fastapi_integration/orm/models.py
fastapi_integration/orm/queries.py
fastapi_integration/orm/signals.py
fastapi_integration/orm/transaction.py
fastapi_integration/orm/utils.py
fastapi_integration/utils/__init__.py
tests/__init__.py
tests/base.py
tests/query/__init__.py
tests/query/test_complex.py
tests/query/test_simple.py
fastapi_integration-0.1.2.dist-info/METADATA
fastapi_integration-0.1.2.dist-info/WHEEL
fastapi_integration-0.1.2.dist-info/top_level.txt
fastapi_integration-0.1.2.dist-info/RECORD
