Metadata-Version: 2.1
Name: fastapi-integration
Version: 0.1.2
Summary: A PyPI package for simplifying FastAPI-ORM integration
Home-page: UNKNOWN
Author: Mani Mozaffar
Author-email: mani.mozaffar@gmail.com
License: UNKNOWN
Platform: UNKNOWN
Requires-Dist: fastapi
Requires-Dist: asyncpg
Requires-Dist: sqlalchemy
Requires-Dist: redis
Requires-Dist: sqladmin
Requires-Dist: pydantic[email]
Requires-Dist: python-dotenv
Requires-Dist: uvicorn
Requires-Dist: passlib
Requires-Dist: pyjwt
